Metadata-Version: 2.1
Name: pandas-appender
Version: 0.9.9
Summary: A helper class that makes appending to a Pandas DataFrame efficient
Home-page: https://github.com/wumpus/pandas-appender
Author: Greg Lindahl and others
Author-email: lindahl@pbm.com
License: Apache 2.0
Platform: UNKNOWN
Classifier: Development Status :: 5 - Production/Stable
Classifier: Environment :: Console
Classifier: Operating System :: POSIX :: Linux
Classifier: Environment :: MacOS X
Classifier: Intended Audience :: Information Technology
Classifier: Intended Audience :: Developers
Classifier: Natural Language :: English
Classifier: License :: OSI Approved :: Apache Software License
Classifier: Programming Language :: Python
Classifier: Programming Language :: Python :: 3.7
Classifier: Programming Language :: Python :: 3.8
Classifier: Programming Language :: Python :: 3.9
Classifier: Programming Language :: Python :: 3.10
Classifier: Programming Language :: Python :: 3.11
Classifier: Programming Language :: Python :: 3.12
Classifier: Programming Language :: Python :: 3 :: Only
Requires-Python: >=3.7
Provides-Extra: test
License-File: LICENSE
